odoo/addons/stock_move_actual_date/README.rst
odoo/addons/stock_move_actual_date/__init__.py
odoo/addons/stock_move_actual_date/__manifest__.py
odoo/addons/stock_move_actual_date/hooks.py
odoo/addons/stock_move_actual_date/i18n/it.po
odoo/addons/stock_move_actual_date/i18n/ja.po
odoo/addons/stock_move_actual_date/i18n/stock_move_actual_date.pot
odoo/addons/stock_move_actual_date/models/__init__.py
odoo/addons/stock_move_actual_date/models/account_move.py
odoo/addons/stock_move_actual_date/models/res_currency.py
odoo/addons/stock_move_actual_date/models/stock_actual_date_mixin.py
odoo/addons/stock_move_actual_date/models/stock_move.py
odoo/addons/stock_move_actual_date/models/stock_move_line.py
odoo/addons/stock_move_actual_date/models/stock_picking.py
odoo/addons/stock_move_actual_date/models/stock_scrap.py
odoo/addons/stock_move_actual_date/models/stock_valuation_layer.py
odoo/addons/stock_move_actual_date/readme/CONFIGURE.md
odoo/addons/stock_move_actual_date/readme/CONTRIBUTORS.md
odoo/addons/stock_move_actual_date/readme/DESCRIPTION.md
odoo/addons/stock_move_actual_date/readme/ROADMAP.md
odoo/addons/stock_move_actual_date/readme/USAGE.md
odoo/addons/stock_move_actual_date/security/stock_move_actual_date_security.xml
odoo/addons/stock_move_actual_date/static/description/icon.png
odoo/addons/stock_move_actual_date/static/description/index.html
odoo/addons/stock_move_actual_date/tests/__init__.py
odoo/addons/stock_move_actual_date/tests/test_stock_move_actual_date.py
odoo/addons/stock_move_actual_date/views/stock_move_line_views.xml
odoo/addons/stock_move_actual_date/views/stock_move_views.xml
odoo/addons/stock_move_actual_date/views/stock_picking_views.xml
odoo/addons/stock_move_actual_date/views/stock_scrap_views.xml
odoo/addons/stock_move_actual_date/views/stock_valuation_layer_views.xml
odoo/addons/stock_move_actual_date/wizard/__init__.py
odoo/addons/stock_move_actual_date/wizard/stock_quantity_history.py
odoo_addon_stock_move_actual_date-18.0.1.0.0.2.dist-info/METADATA
odoo_addon_stock_move_actual_date-18.0.1.0.0.2.dist-info/WHEEL
odoo_addon_stock_move_actual_date-18.0.1.0.0.2.dist-info/top_level.txt
odoo_addon_stock_move_actual_date-18.0.1.0.0.2.dist-info/RECORD
